izihawa_textutils/__init__.py
izihawa_textutils/html_processing.py
izihawa_textutils/regex.py
izihawa_textutils/utils.py
izihawa_textutils-1.0.56.dist-info/METADATA
izihawa_textutils-1.0.56.dist-info/WHEEL
izihawa_textutils-1.0.56.dist-info/RECORD
