Metadata-Version: 2.1
Name: izihawa-textutils
Version: 1.0.56
Summary: 
Author: Pasha Podolsky
Author-email: ppodolsky@me.com
Requires-Python: >=3.8,<4.0
Classifier: Programming Language :: Python :: 3
Classifier: Programming Language :: Python :: 3.8
Classifier: Programming Language :: Python :: 3.9
Classifier: Programming Language :: Python :: 3.10
Classifier: Programming Language :: Python :: 3.11
Classifier: Programming Language :: Python :: 3.12
Requires-Dist: isbnlib (>=3.10.14,<4.0.0)
